independency/__init__.py
independency/container.py
independency-1.4.dist-info/METADATA
independency-1.4.dist-info/WHEEL
independency-1.4.dist-info/licenses/LICENSE
independency-1.4.dist-info/RECORD
