Metadata-Version: 2.4
Name: independency
Version: 1.4
Summary: Dependency injection container
License-File: LICENSE
Author: apollon
Author-email: Apollon76@yandex.ru
Requires-Python: >=3.10,<4.0
Classifier: Programming Language :: Python :: 3
Classifier: Programming Language :: Python :: 3.10
Classifier: Programming Language :: Python :: 3.11
Classifier: Programming Language :: Python :: 3.12
Classifier: Programming Language :: Python :: 3.13
Classifier: Programming Language :: Python :: 3.14
Project-URL: Repository, https://github.com/Apollon76/independency
